chaosify/__init__.py
chaosify/check.py
chaosify/main.py
chaosify/wreck.py
chaosify-0.1.1.dist-info/LICENSE
chaosify-0.1.1.dist-info/METADATA
chaosify-0.1.1.dist-info/WHEEL
chaosify-0.1.1.dist-info/RECORD
