Metadata-Version: 2.1
Name: chaosify
Version: 0.1.1
Summary: 
Author: Yuriy Sannikov
Author-email: yury.sannikov@gmail.com
Requires-Python: >=3.11,<4.0
Classifier: Programming Language :: Python :: 3
Classifier: Programming Language :: Python :: 3.11
Classifier: Programming Language :: Python :: 3.12
